chatterbox
tests
