Metadata-Version: 1.1
Name: django-chatterbox
Version: 0.0.7
Summary: Social listening made easy
Home-page: https://github.com/blitzagency/django-chatterbox
Author: Adam Venturella <aventurella@blitzagency.com>
Author-email: aventurella@blitzagency.com
License: BSD
Keywords: django social chatterbox
Platform: UNKNOWN
Classifier: Development Status :: 2 - Pre-Alpha
Classifier: Intended Audience :: Developers
Classifier: License :: OSI Approved :: BSD License
Classifier: Natural Language :: English
Classifier: Programming Language :: Python :: 2
Classifier: Programming Language :: Python :: 2.6
Classifier: Programming Language :: Python :: 2.7
Classifier: Programming Language :: Python :: 3
Classifier: Programming Language :: Python :: 3.3
